<?xml version="1.0" encoding="UTF-8"?>
<!-- Created with TexturePacker http://www.codeandweb.com/texturepacker-->
<!-- $TexturePacker:SmartUpdate:0b0df3ede1543849c924a923517f27eb:c43ab98ff2e021320e4877951083527d:cde709370900f12288f3449eded86f07$ -->
<TextureAtlas imagePath="atlas.png">
    <SubTexture name="Boy_Happy_0001" x="2" y="2" width="56" height="84"/>
    <SubTexture name="Boy_Happy_0002" x="60" y="2" width="56" height="84"/>
    <SubTexture name="Boy_Happy_0003" x="118" y="2" width="56" height="84"/>
    <SubTexture name="Boy_Happy_0004" x="176" y="2" width="56" height="84"/>
    <SubTexture name="Boy_Happy_0005" x="234" y="2" width="56" height="84"/>
    <SubTexture name="Boy_Happy_0006" x="292" y="2" width="56" height="84"/>
    <SubTexture name="Boy_Happy_0007" x="350" y="2" width="56" height="84"/>
    <SubTexture name="Boy_Happy_0008" x="408" y="2" width="56" height="84"/>
    <SubTexture name="Boy_Happy_0009" x="466" y="2" width="56" height="84"/>
    <SubTexture name="Boy_Happy_0010" x="524" y="2" width="56" height="84"/>
    <SubTexture name="Boy_Happy_0011" x="582" y="2" width="56" height="84"/>
    <SubTexture name="Boy_Happy_0012" x="640" y="2" width="56" height="84"/>
    <SubTexture name="Boy_Happy_0013" x="698" y="2" width="56" height="84"/>
    <SubTexture name="Boy_Happy_0014" x="756" y="2" width="56" height="84"/>
    <SubTexture name="Boy_Happy_0015" x="814" y="2" width="56" height="84"/>
    <SubTexture name="Boy_Happy_0016" x="872" y="2" width="56" height="84"/>
    <SubTexture name="Boy_Happy_0017" x="2" y="88" width="56" height="84"/>
    <SubTexture name="Boy_Happy_0018" x="60" y="88" width="56" height="84"/>
    <SubTexture name="Boy_Happy_0019" x="118" y="88" width="56" height="84"/>
    <SubTexture name="Boy_Happy_0020" x="176" y="88" width="56" height="84"/>
    <SubTexture name="Boy_Happy_0021" x="234" y="88" width="56" height="84"/>
    <SubTexture name="bush" x="292" y="88" width="72" height="43"/>
    <SubTexture name="cat_1" x="366" y="88" width="38" height="38"/>
    <SubTexture name="cat_10" x="406" y="88" width="38" height="38"/>
    <SubTexture name="cat_11" x="446" y="88" width="38" height="38"/>
    <SubTexture name="cat_12" x="486" y="88" width="38" height="38"/>
    <SubTexture name="cat_13" x="526" y="88" width="38" height="38"/>
    <SubTexture name="cat_14" x="566" y="88" width="38" height="38"/>
    <SubTexture name="cat_15" x="606" y="88" width="38" height="38"/>
    <SubTexture name="cat_16" x="646" y="88" width="38" height="38"/>
    <SubTexture name="cat_17" x="686" y="88" width="38" height="38"/>
    <SubTexture name="cat_18" x="726" y="88" width="38" height="38"/>
    <SubTexture name="cat_19" x="766" y="88" width="38" height="38"/>
    <SubTexture name="cat_2" x="366" y="88" width="38" height="38"/>
    <SubTexture name="cat_20" x="766" y="88" width="38" height="38"/>
    <SubTexture name="cat_3" x="366" y="88" width="38" height="38"/>
    <SubTexture name="cat_4" x="366" y="88" width="38" height="38"/>
    <SubTexture name="cat_5" x="366" y="88" width="38" height="38"/>
    <SubTexture name="cat_6" x="366" y="88" width="38" height="38"/>
    <SubTexture name="cat_7" x="366" y="88" width="38" height="38"/>
    <SubTexture name="cat_8" x="806" y="88" width="38" height="38"/>
    <SubTexture name="cat_9" x="846" y="88" width="38" height="38"/>
    <SubTexture name="closed_scene" x="2" y="174" width="483" height="252"/>
    <SubTexture name="cloud" x="487" y="174" width="72" height="86"/>
    <SubTexture name="fluorine" x="561" y="174" width="256" height="256"/>
    <SubTexture name="house" x="819" y="174" width="63" height="104"/>
    <SubTexture name="left_tree" x="884" y="174" width="64" height="121"/>
    <SubTexture name="public" x="2" y="432" width="64" height="84"/>
    <SubTexture name="public_odd" x="68" y="432" width="64" height="84"/>
    <SubTexture name="public_variation" x="134" y="432" width="64" height="84"/>
    <SubTexture name="right_tree" x="200" y="432" width="64" height="121"/>
    <SubTexture name="scene" x="266" y="432" width="680" height="445"/>
    <SubTexture name="top_scene" x="2" y="879" width="680" height="126"/>
</TextureAtlas>
